epeira/__init__.py
epeira/helpers/io_management.py
epeira/helpers/marking.py
epeira/helpers/parsing.py
epeira-0.2.1.dist-info/licenses/LICENSE
epeira-0.2.1.dist-info/METADATA
epeira-0.2.1.dist-info/WHEEL
epeira-0.2.1.dist-info/top_level.txt
epeira-0.2.1.dist-info/RECORD
