Metadata-Version: 2.4
Name: epeira
Version: 0.2.1
Summary: Convenience model tooling for Io Kleiser Consulting.
Requires-Python: >=3.11
License-File: LICENSE
Requires-Dist: pandas>=2.3.1
Requires-Dist: pydantic>=2.11.7
Provides-Extra: dev
Requires-Dist: pytest; extra == "dev"
Requires-Dist: ruff; extra == "dev"
Dynamic: license-file
